setup.cfg
setup.py
fastq_to_SAM_PU/__init__.py
fastq_to_SAM_PU/__main__.py
fastq_to_SAM_PU/main.py
fastq_to_SAM_PU.egg-info/PKG-INFO
fastq_to_SAM_PU.egg-info/SOURCES.txt
fastq_to_SAM_PU.egg-info/dependency_links.txt
fastq_to_SAM_PU.egg-info/entry_points.txt
fastq_to_SAM_PU.egg-info/top_level.txt