Metadata-Version: 1.1
Name: fastq-to-SAM-PU
Version: 0.2
Summary: extract a PU value from a fastq record
Home-page: https://github.com/NCI-GDC/fastq-to-SAM-PU
Author: Jeremiah H. Savage
Author-email: jeremiahsavage@gmail.com
License: Apache 2.0
Platform: UNKNOWN
Classifier: Development Status :: 3 - Alpha
Classifier: Intended Audience :: Developers
Classifier: License :: OSI Approved :: Apache Software License
Classifier: Programming Language :: Python
Classifier: Programming Language :: Python :: 2
Classifier: Programming Language :: Python :: 3
